[{"id": 126639, "name": "Anchor", "file": "16-28.json", "lng": 1085, "lat": 1807, "floor": 1, "rotation": 2, "width": 2, "length": 2, "center": [1086.0, 1808.0], "hash": 353125923, "models": [{"type": 10, "values": [125459]}], "material_replacements": "[[9819,16769]]"}, {"id": 126640, "name": "Anchor", "file": "16-28.json", "lng": 1084, "lat": 1828, "floor": 1, "rotation": 1, "width": 2, "length": 2, "center": [1085.0, 1829.0], "hash": 438271903, "models": [{"type": 10, "values": [130066]}]}, {"id": 124739, "name": "Bench", "file": "16-28.json", "lng": 1080, "lat": 1813, "floor": 1, "rotation": 0, "length": 2, "center": [1080.5, 1814.0], "hash": 910605735, "actions": ["Sit on"], "models": [{"type": 10, "values": [127067]}], "dummy_45": 13}, {"id": 126864, "name": "Barrel", "file": "16-28.json", "lng": 1084, "lat": 1807, "floor": 1, "rotation": 1, "center": [1084.5, 1807.5], "hash": 3445910797, "models": [{"type": 10, "values": [67867]}]}, {"id": 126866, "name": "Barrel", "file": "16-28.json", "lng": 1086, "lat": 1804, "floor": 1, "rotation": 1, "center": [1086.5, 1804.5], "hash": 1388416071, "models": [{"type": 10, "values": [67868]}]}, {"id": 126867, "name": "Barrel", "file": "16-28.json", "lng": 1086, "lat": 1805, "floor": 1, "rotation": 1, "center": [1086.5, 1805.5], "hash": 3948607145, "models": [{"type": 10, "values": [67869]}]}, {"id": 126868, "name": "Barrel", "file": "16-28.json", "lng": 1085, "lat": 1817, "floor": 1, "rotation": 0, "center": [1085.5, 1817.5], "hash": 1871433382, "models": [{"type": 10, "values": [67889]}], "dummy_bc": true}, {"id": 126870, "name": "Barrel", "file": "16-28.json", "lng": 1086, "lat": 1826, "floor": 1, "rotation": 0, "center": [1086.5, 1826.5], "hash": 42223742, "models": [{"type": 10, "values": [67891]}]}, {"id": 126843, "name": "Cart", "file": "16-28.json", "lng": 1084, "lat": 1805, "floor": 1, "rotation": 1, "width": 4, "length": 2, "center": [1086.0, 1806.0], "hash": 3704191049, "models": [{"type": 10, "values": [89336]}]}, {"id": 126872, "name": "Crate", "file": "16-28.json", "lng": 1080, "lat": 1817, "floor": 1, "rotation": 1, "center": [1080.5, 1817.5], "hash": 1860108048, "models": [{"type": 10, "values": [73976]}]}, {"id": 126872, "name": "Crate", "file": "16-28.json", "lng": 1081, "lat": 1804, "floor": 1, "rotation": 2, "center": [1081.5, 1804.5], "hash": 1964304277, "models": [{"type": 10, "values": [73976]}]}, {"id": 126872, "name": "Crate", "file": "16-28.json", "lng": 1085, "lat": 1805, "floor": 1, "rotation": 2, "center": [1085.5, 1805.5], "hash": 2498456537, "models": [{"type": 10, "values": [73976]}]}, {"id": 126874, "name": "Crate", "file": "16-28.json", "lng": 1080, "lat": 1805, "floor": 1, "rotation": 2, "center": [1080.5, 1805.5], "hash": 1072162578, "models": [{"type": 10, "values": [74102]}]}, {"id": 126874, "name": "Crate", "file": "16-28.json", "lng": 1086, "lat": 1818, "floor": 1, "rotation": 1, "center": [1086.5, 1818.5], "hash": 623270109, "models": [{"type": 10, "values": [74102]}]}, {"id": 126875, "name": "Crate", "file": "16-28.json", "lng": 1084, "lat": 1818, "floor": 1, "rotation": 1, "center": [1084.5, 1818.5], "hash": 2473863828, "models": [{"type": 10, "values": [74103]}]}, {"id": 126479, "name": "Dock", "file": "16-28.json", "lng": 1083, "lat": 1803, "floor": 1, "rotation": 3, "center": [1083.5, 1803.5], "hash": 1528566058, "actions": ["Disembark"], "models": [{"type": 10, "values": [67768]}], "material_replacements": "[[8868,11042]]"}, {"id": 126199, "name": "Gondola", "file": "16-28.json", "lng": 1077, "lat": 1806, "floor": 1, "rotation": 2, "length": 10, "center": [1077.5, 1811.0], "hash": 114175807, "models": [{"type": 10, "values": [128844]}]}, {"id": 130745, "name": "Gondola", "file": "16-28.json", "lng": 1078, "lat": 1821, "floor": 1, "rotation": 1, "length": 8, "center": [1078.5, 1825.0], "hash": 2750223930, "models": [{"type": 10, "values": [128846]}], "morphs_1": {"unk1": 3658153983, "unk2": [126197, 126197, 126197, 126197, 126197, 126197, 126197, 126197, 126197, 126197, 126197, 126197, 126197, 126197, 126197, 126197, 126197, 126197, 126197, 126197, 126197, 126197, 126197, 126197, 126197, 126197, 126197, 126197, 126197, 126197, 126197, 126197, 126197, 126197, 126197, 126197, 126197, 126197, 126197, 126197, 126197, 32767, 32767, 32767, 32767, 130746, 130746, 130746, 130746, 130746, 130746, 130746, 130746, 130746, 130746, 130746, 130746, 130746, 130746, 130746, 130746, 130746, 130746, 130746, 130746], "unk3": 130746}}, {"id": 126877, "name": "Sack", "file": "16-28.json", "lng": 1087, "lat": 1826, "floor": 1, "rotation": 0, "center": [1087.5, 1826.5], "hash": 4279026900, "models": [{"type": 10, "values": [74105]}], "dummy_bc": true}, {"id": 126878, "name": "Sack", "file": "16-28.json", "lng": 1085, "lat": 1806, "floor": 1, "rotation": 1, "center": [1085.5, 1806.5], "hash": 2481998875, "models": [{"type": 10, "values": [74106]}], "dummy_bc": true}, {"id": 126878, "name": "Sack", "file": "16-28.json", "lng": 1087, "lat": 1818, "floor": 1, "rotation": 1, "center": [1087.5, 1818.5], "hash": 2468080299, "models": [{"type": 10, "values": [74106]}], "dummy_bc": true}, {"id": 126938, "name": "Taxi sign", "file": "16-28.json", "lng": 1086, "lat": 1832, "floor": 1, "rotation": 2, "width": 2, "center": [1087.0, 1832.5], "hash": 1000166893, "models": [{"type": 10, "values": [128891]}]}]