[{"id": 111607, "name": "Bed", "file": "39-181.json", "lng": 2524, "lat": 11599, "floor": 0, "rotation": 2, "length": 2, "center": [2524.5, 11600.0], "hash": 3003457236, "models": [{"type": 10, "values": [76006]}]}, {"id": 111608, "name": "Bed", "file": "39-181.json", "lng": 2552, "lat": 11602, "floor": 0, "rotation": 2, "length": 2, "center": [2552.5, 11603.0], "hash": 3943865798, "models": [{"type": 10, "values": [76006, 76004]}]}, {"id": 111608, "name": "Bed", "file": "39-181.json", "lng": 2553, "lat": 11599, "floor": 0, "rotation": 0, "length": 2, "center": [2553.5, 11600.0], "hash": 834092619, "models": [{"type": 10, "values": [76006, 76004]}]}, {"id": 111608, "name": "Bed", "file": "39-181.json", "lng": 2555, "lat": 11599, "floor": 0, "rotation": 0, "length": 2, "center": [2555.5, 11600.0], "hash": 834092619, "models": [{"type": 10, "values": [76006, 76004]}]}, {"id": 111608, "name": "Bed", "file": "39-181.json", "lng": 2555, "lat": 11602, "floor": 0, "rotation": 2, "length": 2, "center": [2555.5, 11603.0], "hash": 3943865798, "models": [{"type": 10, "values": [76006, 76004]}]}, {"id": 111609, "name": "Bed", "file": "39-181.json", "lng": 2526, "lat": 11606, "floor": 0, "rotation": 2, "length": 2, "center": [2526.5, 11607.0], "hash": 1041752506, "models": [{"type": 10, "values": [118292]}]}, {"id": 111609, "name": "Bed", "file": "39-181.json", "lng": 2526, "lat": 11608, "floor": 0, "rotation": 0, "length": 2, "center": [2526.5, 11609.0], "hash": 3836887607, "models": [{"type": 10, "values": [118292]}]}, {"id": 111609, "name": "Bed", "file": "39-181.json", "lng": 2529, "lat": 11606, "floor": 0, "rotation": 1, "length": 2, "center": [2529.5, 11607.0], "hash": 2816991788, "models": [{"type": 10, "values": [118292]}]}, {"id": 111611, "name": "Beds", "file": "39-181.json", "lng": 2527, "lat": 11607, "floor": 0, "rotation": 3, "width": 2, "length": 3, "center": [2528.0, 11608.5], "hash": 3422482891, "models": [{"type": 10, "values": [118291]}]}, {"id": 111611, "name": "Beds", "file": "39-181.json", "lng": 2543, "lat": 11612, "floor": 0, "rotation": 2, "width": 2, "length": 3, "center": [2544.0, 11613.5], "hash": 1439260039, "models": [{"type": 10, "values": [118291]}]}, {"id": 111613, "name": "Basket", "file": "39-181.json", "lng": 2527, "lat": 11609, "floor": 0, "rotation": 2, "center": [2527.5, 11609.5], "hash": 3705674952, "models": [{"type": 10, "values": [75974]}]}, {"id": 111616, "name": "Basket", "file": "39-181.json", "lng": 2526, "lat": 11602, "floor": 0, "rotation": 2, "center": [2526.5, 11602.5], "hash": 568388820, "models": [{"type": 10, "values": [75986]}]}, {"id": 111617, "name": "Basket", "file": "39-181.json", "lng": 2527, "lat": 11606, "floor": 0, "rotation": 1, "center": [2527.5, 11606.5], "hash": 2930401731, "models": [{"type": 10, "values": [75984]}]}, {"id": 111617, "name": "Basket", "file": "39-181.json", "lng": 2528, "lat": 11609, "floor": 0, "rotation": 2, "center": [2528.5, 11609.5], "hash": 4108685480, "models": [{"type": 10, "values": [75984]}]}, {"id": 5780, "name": "Cora's log", "file": "39-181.json", "lng": 2556, "lat": 11588, "floor": 0, "rotation": 0, "center": [2556.5, 11588.5], "hash": 648161004, "actions": ["Read"], "models": [{"type": 22, "values": [17671]}], "action_cursors_0": 50}, {"id": 102810, "name": "Charms", "file": "39-181.json", "lng": 2550, "lat": 11602, "floor": 0, "rotation": 2, "center": [2550.5, 11602.5], "hash": 4288687524, "models": [{"type": 4, "values": [112150]}]}, {"id": 104868, "name": "Corpse", "file": "39-181.json", "lng": 2506, "lat": 11585, "floor": 0, "rotation": 2, "length": 2, "center": [2506.5, 11586.0], "hash": 3836351606, "models": [{"type": 10, "values": [114932]}]}, {"id": 104870, "name": "Corpse", "file": "39-181.json", "lng": 2506, "lat": 11603, "floor": 0, "rotation": 2, "length": 2, "center": [2506.5, 11604.0], "hash": 743476930, "models": [{"type": 10, "values": [114934]}]}, {"id": 104870, "name": "Corpse", "file": "39-181.json", "lng": 2508, "lat": 11592, "floor": 0, "rotation": 2, "length": 2, "center": [2508.5, 11593.0], "hash": 2435389222, "models": [{"type": 10, "values": [114934]}]}, {"id": 104871, "name": "Corpse", "file": "39-181.json", "lng": 2501, "lat": 11584, "floor": 0, "rotation": 3, "length": 2, "center": [2501.5, 11585.0], "hash": 2562789764, "models": [{"type": 10, "values": [114929]}]}, {"id": 104871, "name": "Corpse", "file": "39-181.json", "lng": 2507, "lat": 11596, "floor": 0, "rotation": 2, "length": 2, "center": [2507.5, 11597.0], "hash": 3627006226, "models": [{"type": 10, "values": [114929]}]}, {"id": 104872, "name": "Corpse", "file": "39-181.json", "lng": 2499, "lat": 11598, "floor": 0, "rotation": 3, "length": 2, "center": [2499.5, 11599.0], "hash": 1408519609, "models": [{"type": 10, "values": [114930]}]}, {"id": 104872, "name": "Corpse", "file": "39-181.json", "lng": 2509, "lat": 11598, "floor": 0, "rotation": 2, "length": 2, "center": [2509.5, 11599.0], "hash": 2223533205, "models": [{"type": 10, "values": [114930]}]}, {"id": 104873, "name": "Corpse", "file": "39-181.json", "lng": 2503, "lat": 11600, "floor": 0, "rotation": 2, "center": [2503.5, 11600.5], "hash": 3452332509, "models": [{"type": 10, "values": [114931]}]}, {"id": 111649, "name": "Cupboard", "file": "39-181.json", "lng": 2553, "lat": 11603, "floor": 0, "rotation": 2, "width": 2, "center": [2554.0, 11603.5], "hash": 2501648055, "models": [{"type": 10, "values": [118303]}]}, {"id": 111651, "name": "Crate", "file": "39-181.json", "lng": 2538, "lat": 11609, "floor": 0, "rotation": 0, "length": 2, "center": [2538.5, 11610.0], "hash": 819772996, "models": [{"type": 10, "values": [113419]}]}, {"id": 111653, "name": "Crate", "file": "39-181.json", "lng": 2528, "lat": 11605, "floor": 0, "rotation": 0, "center": [2528.5, 11605.5], "hash": 540916987, "models": [{"type": 10, "values": [113421]}]}, {"id": 2097, "name": "Gate of Goshima", "file": "39-181.json", "lng": 2519, "lat": 11588, "floor": 0, "rotation": 0, "width": 2, "length": 5, "center": [2520.0, 11590.5], "hash": 4020874577, "models": [{"type": 10, "values": [74722]}], "morphs_1": {"unk1": 2847145983, "unk2": [2098], "unk3": 2099}}, {"id": 104653, "name": "Mushroom cluster", "file": "39-181.json", "lng": 2510, "lat": 11598, "floor": 0, "rotation": 3, "center": [2510.5, 11598.5], "hash": 2578963861, "actions": ["Forage"], "models": [{"type": 10, "values": [114906]}], "action_cursors_0": 171}, {"id": 104990, "name": "Note", "file": "39-181.json", "lng": 2507, "lat": 11595, "floor": 0, "rotation": 0, "center": [2507.5, 11595.5], "hash": 3691621551, "models": [{"type": 10, "values": [114703]}], "morphs_1": {"unk1": 2224816127, "unk2": [104991, 104992], "unk3": 104993}}, {"id": 111621, "name": "Pillow", "file": "39-181.json", "lng": 2525, "lat": 11602, "floor": 0, "rotation": 1, "center": [2525.5, 11602.5], "hash": 1281203377, "models": [{"type": 10, "values": [4971]}]}, {"id": 111621, "name": "Pillow", "file": "39-181.json", "lng": 2538, "lat": 11611, "floor": 0, "rotation": 3, "center": [2538.5, 11611.5], "hash": 1135421690, "models": [{"type": 10, "values": [4971]}]}, {"id": 111621, "name": "Pillow", "file": "39-181.json", "lng": 2553, "lat": 11590, "floor": 0, "rotation": 3, "center": [2553.5, 11590.5], "hash": 2532851516, "models": [{"type": 10, "values": [4971]}]}, {"id": 111661, "name": "Pot", "file": "39-181.json", "lng": 2555, "lat": 11590, "floor": 0, "rotation": 2, "center": [2555.5, 11590.5], "hash": 2984183871, "models": [{"type": 10, "values": [82131]}]}, {"id": 5779, "name": "Soul vampyres", "file": "39-181.json", "lng": 2526, "lat": 11599, "floor": 0, "rotation": 0, "center": [2526.5, 11599.5], "hash": 1613453659, "actions": ["Read"], "models": [{"type": 22, "values": [17671]}], "action_cursors_0": 50}, {"id": 15158, "name": "Standing torch", "file": "39-181.json", "lng": 2529, "lat": 11597, "floor": 0, "rotation": 0, "center": [2529.5, 11597.5], "hash": 1225921066, "models": [{"type": 10, "values": [5439]}], "color_replacements": "[[6707,7463],[5669,7582],[5788,7582]]"}, {"id": 15158, "name": "Standing torch", "file": "39-181.json", "lng": 2540, "lat": 11610, "floor": 0, "rotation": 0, "center": [2540.5, 11610.5], "hash": 2952604293, "models": [{"type": 10, "values": [5439]}], "color_replacements": "[[6707,7463],[5669,7582],[5788,7582]]"}, {"id": 15158, "name": "Standing torch", "file": "39-181.json", "lng": 2551, "lat": 11605, "floor": 0, "rotation": 3, "center": [2551.5, 11605.5], "hash": 798631639, "models": [{"type": 10, "values": [5439]}], "color_replacements": "[[6707,7463],[5669,7582],[5788,7582]]"}, {"id": 15158, "name": "Standing torch", "file": "39-181.json", "lng": 2554, "lat": 11587, "floor": 0, "rotation": 2, "center": [2554.5, 11587.5], "hash": 1968736520, "models": [{"type": 10, "values": [5439]}], "color_replacements": "[[6707,7463],[5669,7582],[5788,7582]]"}, {"id": 111629, "name": "Straw", "file": "39-181.json", "lng": 2528, "lat": 11603, "floor": 0, "rotation": 3, "width": 2, "length": 3, "center": [2529.0, 11604.5], "hash": 1968581097, "models": [{"type": 10, "values": [91112]}]}, {"id": 111629, "name": "Straw", "file": "39-181.json", "lng": 2544, "lat": 11584, "floor": 0, "rotation": 3, "width": 2, "length": 3, "center": [2545.0, 11585.5], "hash": 3011199838, "models": [{"type": 10, "values": [91112]}]}, {"id": 15250, "name": "Trunk", "file": "39-181.json", "lng": 2524, "lat": 11602, "floor": 0, "rotation": 0, "center": [2524.5, 11602.5], "hash": 3334963878, "actions": ["Open"], "models": [{"type": 10, "values": [118298]}], "action_cursors_0": 49}, {"id": 15250, "name": "Trunk", "file": "39-181.json", "lng": 2536, "lat": 11614, "floor": 0, "rotation": 0, "center": [2536.5, 11614.5], "hash": 328373600, "actions": ["Open"], "models": [{"type": 10, "values": [118298]}], "action_cursors_0": 49}, {"id": 15250, "name": "Trunk", "file": "39-181.json", "lng": 2544, "lat": 11615, "floor": 0, "rotation": 2, "center": [2544.5, 11615.5], "hash": 684232596, "actions": ["Open"], "models": [{"type": 10, "values": [118298]}], "action_cursors_0": 49}, {"id": 15250, "name": "Trunk", "file": "39-181.json", "lng": 2545, "lat": 11615, "floor": 0, "rotation": 2, "center": [2545.5, 11615.5], "hash": 684232596, "actions": ["Open"], "models": [{"type": 10, "values": [118298]}], "action_cursors_0": 49}, {"id": 15250, "name": "Trunk", "file": "39-181.json", "lng": 2550, "lat": 11599, "floor": 0, "rotation": 1, "center": [2550.5, 11599.5], "hash": 1375111750, "actions": ["Open"], "models": [{"type": 10, "values": [118298]}], "action_cursors_0": 49}, {"id": 15250, "name": "Trunk", "file": "39-181.json", "lng": 2551, "lat": 11604, "floor": 0, "rotation": 2, "center": [2551.5, 11604.5], "hash": 992865185, "actions": ["Open"], "models": [{"type": 10, "values": [118298]}], "action_cursors_0": 49}, {"id": 111662, "name": "Vase", "file": "39-181.json", "lng": 2554, "lat": 11591, "floor": 0, "rotation": 2, "center": [2554.5, 11591.5], "hash": 41603324, "models": [{"type": 10, "values": [113484]}]}]