[{"id": 1282, "name": "Dead tree", "file": "53-71.json", "lng": 3393, "lat": 4578, "floor": 0, "rotation": 1, "width": 2, "length": 2, "center": [3394.0, 4579.0], "hash": 4248550291, "actions": ["Chop down"], "models": [{"type": 10, "values": [85098]}], "treerockordoor_BD": true, "action_cursors_0": 59}, {"id": 1282, "name": "Dead tree", "file": "53-71.json", "lng": 3394, "lat": 4598, "floor": 0, "rotation": 0, "width": 2, "length": 2, "center": [3395.0, 4599.0], "hash": 133918095, "actions": ["Chop down"], "models": [{"type": 10, "values": [85098]}], "treerockordoor_BD": true, "action_cursors_0": 59}, {"id": 1282, "name": "Dead tree", "file": "53-71.json", "lng": 3398, "lat": 4577, "floor": 0, "rotation": 3, "width": 2, "length": 2, "center": [3399.0, 4578.0], "hash": 2151391668, "actions": ["Chop down"], "models": [{"type": 10, "values": [85098]}], "treerockordoor_BD": true, "action_cursors_0": 59}, {"id": 1282, "name": "Dead tree", "file": "53-71.json", "lng": 3399, "lat": 4567, "floor": 0, "rotation": 0, "width": 2, "length": 2, "center": [3400.0, 4568.0], "hash": 2404530437, "actions": ["Chop down"], "models": [{"type": 10, "values": [85098]}], "treerockordoor_BD": true, "action_cursors_0": 59}, {"id": 1282, "name": "Dead tree", "file": "53-71.json", "lng": 3399, "lat": 4587, "floor": 0, "rotation": 0, "width": 2, "length": 2, "center": [3400.0, 4588.0], "hash": 173825684, "actions": ["Chop down"], "models": [{"type": 10, "values": [85098]}], "treerockordoor_BD": true, "action_cursors_0": 59}, {"id": 1282, "name": "Dead tree", "file": "53-71.json", "lng": 3400, "lat": 4596, "floor": 0, "rotation": 1, "width": 2, "length": 2, "center": [3401.0, 4597.0], "hash": 3913633178, "actions": ["Chop down"], "models": [{"type": 10, "values": [85098]}], "treerockordoor_BD": true, "action_cursors_0": 59}, {"id": 1282, "name": "Dead tree", "file": "53-71.json", "lng": 3406, "lat": 4572, "floor": 0, "rotation": 1, "width": 2, "length": 2, "center": [3407.0, 4573.0], "hash": 2923303576, "actions": ["Chop down"], "models": [{"type": 10, "values": [85098]}], "treerockordoor_BD": true, "action_cursors_0": 59}, {"id": 1282, "name": "Dead tree", "file": "53-71.json", "lng": 3406, "lat": 4583, "floor": 0, "rotation": 2, "width": 2, "length": 2, "center": [3407.0, 4584.0], "hash": 1652952300, "actions": ["Chop down"], "models": [{"type": 10, "values": [85098]}], "treerockordoor_BD": true, "action_cursors_0": 59}, {"id": 1282, "name": "Dead tree", "file": "53-71.json", "lng": 3407, "lat": 4558, "floor": 0, "rotation": 3, "width": 2, "length": 2, "center": [3408.0, 4559.0], "hash": 1134354122, "actions": ["Chop down"], "models": [{"type": 10, "values": [85098]}], "treerockordoor_BD": true, "action_cursors_0": 59}, {"id": 1282, "name": "Dead tree", "file": "53-71.json", "lng": 3412, "lat": 4576, "floor": 0, "rotation": 3, "width": 2, "length": 2, "center": [3413.0, 4577.0], "hash": 3520452822, "actions": ["Chop down"], "models": [{"type": 10, "values": [85098]}], "treerockordoor_BD": true, "action_cursors_0": 59}, {"id": 1282, "name": "Dead tree", "file": "53-71.json", "lng": 3413, "lat": 4570, "floor": 0, "rotation": 2, "width": 2, "length": 2, "center": [3414.0, 4571.0], "hash": 1273441864, "actions": ["Chop down"], "models": [{"type": 10, "values": [85098]}], "treerockordoor_BD": true, "action_cursors_0": 59}, {"id": 1282, "name": "Dead tree", "file": "53-71.json", "lng": 3420, "lat": 4570, "floor": 0, "rotation": 0, "width": 2, "length": 2, "center": [3421.0, 4571.0], "hash": 4290611134, "actions": ["Chop down"], "models": [{"type": 10, "values": [85098]}], "treerockordoor_BD": true, "action_cursors_0": 59}, {"id": 1282, "name": "Dead tree", "file": "53-71.json", "lng": 3430, "lat": 4571, "floor": 0, "rotation": 2, "width": 2, "length": 2, "center": [3431.0, 4572.0], "hash": 1428477786, "actions": ["Chop down"], "models": [{"type": 10, "values": [85098]}], "treerockordoor_BD": true, "action_cursors_0": 59}, {"id": 1282, "name": "Dead tree", "file": "53-71.json", "lng": 3434, "lat": 4577, "floor": 0, "rotation": 3, "width": 2, "length": 2, "center": [3435.0, 4578.0], "hash": 986601314, "actions": ["Chop down"], "models": [{"type": 10, "values": [85098]}], "treerockordoor_BD": true, "action_cursors_0": 59}, {"id": 1282, "name": "Dead tree", "file": "53-71.json", "lng": 3439, "lat": 4571, "floor": 0, "rotation": 1, "width": 2, "length": 2, "center": [3440.0, 4572.0], "hash": 904340725, "actions": ["Chop down"], "models": [{"type": 10, "values": [85098]}], "treerockordoor_BD": true, "action_cursors_0": 59}, {"id": 1286, "name": "Dead tree", "file": "53-71.json", "lng": 3392, "lat": 4584, "floor": 0, "rotation": 2, "center": [3392.5, 4584.5], "hash": 466126731, "actions": ["Chop down"], "models": [{"type": 10, "values": [85107]}], "treerockordoor_BD": true, "action_cursors_0": 59}, {"id": 1286, "name": "Dead tree", "file": "53-71.json", "lng": 3395, "lat": 4575, "floor": 0, "rotation": 0, "center": [3395.5, 4575.5], "hash": 349024243, "actions": ["Chop down"], "models": [{"type": 10, "values": [85107]}], "treerockordoor_BD": true, "action_cursors_0": 59}, {"id": 1286, "name": "Dead tree", "file": "53-71.json", "lng": 3396, "lat": 4582, "floor": 0, "rotation": 3, "center": [3396.5, 4582.5], "hash": 1622909046, "actions": ["Chop down"], "models": [{"type": 10, "values": [85107]}], "treerockordoor_BD": true, "action_cursors_0": 59}, {"id": 1286, "name": "Dead tree", "file": "53-71.json", "lng": 3396, "lat": 4591, "floor": 0, "rotation": 0, "center": [3396.5, 4591.5], "hash": 2876260950, "actions": ["Chop down"], "models": [{"type": 10, "values": [85107]}], "treerockordoor_BD": true, "action_cursors_0": 59}, {"id": 1286, "name": "Dead tree", "file": "53-71.json", "lng": 3397, "lat": 4593, "floor": 0, "rotation": 3, "center": [3397.5, 4593.5], "hash": 3535009262, "actions": ["Chop down"], "models": [{"type": 10, "values": [85107]}], "treerockordoor_BD": true, "action_cursors_0": 59}, {"id": 1286, "name": "Dead tree", "file": "53-71.json", "lng": 3398, "lat": 4601, "floor": 0, "rotation": 3, "center": [3398.5, 4601.5], "hash": 2519221563, "actions": ["Chop down"], "models": [{"type": 10, "values": [85107]}], "treerockordoor_BD": true, "action_cursors_0": 59}, {"id": 1286, "name": "Dead tree", "file": "53-71.json", "lng": 3399, "lat": 4572, "floor": 0, "rotation": 1, "center": [3399.5, 4572.5], "hash": 1198407510, "actions": ["Chop down"], "models": [{"type": 10, "values": [85107]}], "treerockordoor_BD": true, "action_cursors_0": 59}, {"id": 1286, "name": "Dead tree", "file": "53-71.json", "lng": 3400, "lat": 4584, "floor": 0, "rotation": 2, "center": [3400.5, 4584.5], "hash": 1680635931, "actions": ["Chop down"], "models": [{"type": 10, "values": [85107]}], "treerockordoor_BD": true, "action_cursors_0": 59}, {"id": 1286, "name": "Dead tree", "file": "53-71.json", "lng": 3403, "lat": 4577, "floor": 0, "rotation": 2, "center": [3403.5, 4577.5], "hash": 1559458264, "actions": ["Chop down"], "models": [{"type": 10, "values": [85107]}], "treerockordoor_BD": true, "action_cursors_0": 59}, {"id": 1286, "name": "Dead tree", "file": "53-71.json", "lng": 3404, "lat": 4587, "floor": 0, "rotation": 1, "center": [3404.5, 4587.5], "hash": 2862350177, "actions": ["Chop down"], "models": [{"type": 10, "values": [85107]}], "treerockordoor_BD": true, "action_cursors_0": 59}, {"id": 1286, "name": "Dead tree", "file": "53-71.json", "lng": 3406, "lat": 4569, "floor": 0, "rotation": 3, "center": [3406.5, 4569.5], "hash": 2078115084, "actions": ["Chop down"], "models": [{"type": 10, "values": [85107]}], "treerockordoor_BD": true, "action_cursors_0": 59}, {"id": 1286, "name": "Dead tree", "file": "53-71.json", "lng": 3410, "lat": 4563, "floor": 0, "rotation": 2, "center": [3410.5, 4563.5], "hash": 1849104838, "actions": ["Chop down"], "models": [{"type": 10, "values": [85107]}], "treerockordoor_BD": true, "action_cursors_0": 59}, {"id": 1286, "name": "Dead tree", "file": "53-71.json", "lng": 3410, "lat": 4565, "floor": 0, "rotation": 1, "center": [3410.5, 4565.5], "hash": 681499196, "actions": ["Chop down"], "models": [{"type": 10, "values": [85107]}], "treerockordoor_BD": true, "action_cursors_0": 59}, {"id": 1286, "name": "Dead tree", "file": "53-71.json", "lng": 3410, "lat": 4573, "floor": 0, "rotation": 0, "center": [3410.5, 4573.5], "hash": 3181633297, "actions": ["Chop down"], "models": [{"type": 10, "values": [85107]}], "treerockordoor_BD": true, "action_cursors_0": 59}, {"id": 1286, "name": "Dead tree", "file": "53-71.json", "lng": 3411, "lat": 4581, "floor": 0, "rotation": 0, "center": [3411.5, 4581.5], "hash": 3434613632, "actions": ["Chop down"], "models": [{"type": 10, "values": [85107]}], "treerockordoor_BD": true, "action_cursors_0": 59}, {"id": 1286, "name": "Dead tree", "file": "53-71.json", "lng": 3412, "lat": 4544, "floor": 0, "rotation": 0, "center": [3412.5, 4544.5], "hash": 4036553982, "actions": ["Chop down"], "models": [{"type": 10, "values": [85107]}], "treerockordoor_BD": true, "action_cursors_0": 59}, {"id": 1286, "name": "Dead tree", "file": "53-71.json", "lng": 3415, "lat": 4545, "floor": 0, "rotation": 2, "center": [3415.5, 4545.5], "hash": 219880140, "actions": ["Chop down"], "models": [{"type": 10, "values": [85107]}], "treerockordoor_BD": true, "action_cursors_0": 59}, {"id": 1286, "name": "Dead tree", "file": "53-71.json", "lng": 3415, "lat": 4566, "floor": 0, "rotation": 3, "center": [3415.5, 4566.5], "hash": 3442580040, "actions": ["Chop down"], "models": [{"type": 10, "values": [85107]}], "treerockordoor_BD": true, "action_cursors_0": 59}, {"id": 1286, "name": "Dead tree", "file": "53-71.json", "lng": 3417, "lat": 4573, "floor": 0, "rotation": 0, "center": [3417.5, 4573.5], "hash": 3434613632, "actions": ["Chop down"], "models": [{"type": 10, "values": [85107]}], "treerockordoor_BD": true, "action_cursors_0": 59}, {"id": 1286, "name": "Dead tree", "file": "53-71.json", "lng": 3421, "lat": 4548, "floor": 0, "rotation": 1, "center": [3421.5, 4548.5], "hash": 1467622828, "actions": ["Chop down"], "models": [{"type": 10, "values": [85107]}], "treerockordoor_BD": true, "action_cursors_0": 59}, {"id": 1286, "name": "Dead tree", "file": "53-71.json", "lng": 3421, "lat": 4564, "floor": 0, "rotation": 3, "center": [3421.5, 4564.5], "hash": 3380727005, "actions": ["Chop down"], "models": [{"type": 10, "values": [85107]}], "treerockordoor_BD": true, "action_cursors_0": 59}, {"id": 1286, "name": "Dead tree", "file": "53-71.json", "lng": 3422, "lat": 4573, "floor": 0, "rotation": 1, "center": [3422.5, 4573.5], "hash": 110251704, "actions": ["Chop down"], "models": [{"type": 10, "values": [85107]}], "treerockordoor_BD": true, "action_cursors_0": 59}, {"id": 1286, "name": "Dead tree", "file": "53-71.json", "lng": 3426, "lat": 4568, "floor": 0, "rotation": 2, "center": [3426.5, 4568.5], "hash": 3992850260, "actions": ["Chop down"], "models": [{"type": 10, "values": [85107]}], "treerockordoor_BD": true, "action_cursors_0": 59}, {"id": 1286, "name": "Dead tree", "file": "53-71.json", "lng": 3433, "lat": 4564, "floor": 0, "rotation": 0, "center": [3433.5, 4564.5], "hash": 1215998304, "actions": ["Chop down"], "models": [{"type": 10, "values": [85107]}], "treerockordoor_BD": true, "action_cursors_0": 59}, {"id": 1286, "name": "Dead tree", "file": "53-71.json", "lng": 3435, "lat": 4571, "floor": 0, "rotation": 1, "center": [3435.5, 4571.5], "hash": 560612687, "actions": ["Chop down"], "models": [{"type": 10, "values": [85107]}], "treerockordoor_BD": true, "action_cursors_0": 59}, {"id": 1286, "name": "Dead tree", "file": "53-71.json", "lng": 3436, "lat": 4565, "floor": 0, "rotation": 0, "center": [3436.5, 4565.5], "hash": 3648330162, "actions": ["Chop down"], "models": [{"type": 10, "values": [85107]}], "treerockordoor_BD": true, "action_cursors_0": 59}, {"id": 1286, "name": "Dead tree", "file": "53-71.json", "lng": 3444, "lat": 4568, "floor": 0, "rotation": 3, "center": [3444.5, 4568.5], "hash": 2026048121, "actions": ["Chop down"], "models": [{"type": 10, "values": [85107]}], "treerockordoor_BD": true, "action_cursors_0": 59}, {"id": 41713, "name": "Dead tree", "file": "53-71.json", "lng": 3433, "lat": 4581, "floor": 0, "rotation": 3, "center": [3433.5, 4581.5], "hash": 332828225, "actions": ["Chop down"], "models": [{"type": 10, "values": [45222]}], "color_replacements": "[[6028,3470],[7054,3470]]", "action_cursors_0": 59}, {"id": 41713, "name": "Dead tree", "file": "53-71.json", "lng": 3436, "lat": 4584, "floor": 0, "rotation": 3, "center": [3436.5, 4584.5], "hash": 4142568209, "actions": ["Chop down"], "models": [{"type": 10, "values": [45222]}], "color_replacements": "[[6028,3470],[7054,3470]]", "action_cursors_0": 59}, {"id": 41713, "name": "Dead tree", "file": "53-71.json", "lng": 3438, "lat": 4580, "floor": 0, "rotation": 0, "center": [3438.5, 4580.5], "hash": 1540651763, "actions": ["Chop down"], "models": [{"type": 10, "values": [45222]}], "color_replacements": "[[6028,3470],[7054,3470]]", "action_cursors_0": 59}, {"id": 41704, "name": "Iced rocks", "file": "53-71.json", "lng": 3434, "lat": 4588, "floor": 0, "rotation": 2, "center": [3434.5, 4588.5], "hash": 4101049909, "models": [{"type": 10, "values": [45213]}], "probably_morphFloor": true}, {"id": 41704, "name": "Iced rocks", "file": "53-71.json", "lng": 3439, "lat": 4582, "floor": 0, "rotation": 1, "center": [3439.5, 4582.5], "hash": 2752574697, "models": [{"type": 10, "values": [45213]}], "probably_morphFloor": true}, {"id": 41704, "name": "Iced rocks", "file": "53-71.json", "lng": 3440, "lat": 4598, "floor": 0, "rotation": 0, "center": [3440.5, 4598.5], "hash": 3064315928, "models": [{"type": 10, "values": [45213]}], "probably_morphFloor": true}, {"id": 41705, "name": "Iced rocks", "file": "53-71.json", "lng": 3441, "lat": 4601, "floor": 0, "rotation": 3, "center": [3441.5, 4601.5], "hash": 3958355765, "models": [{"type": 10, "values": [45225]}], "probably_morphFloor": true}, {"id": 41706, "name": "Iced rocks", "file": "53-71.json", "lng": 3431, "lat": 4588, "floor": 0, "rotation": 1, "center": [3431.5, 4588.5], "hash": 3562390215, "models": [{"type": 10, "values": [45214]}], "probably_morphFloor": true}, {"id": 41706, "name": "Iced rocks", "file": "53-71.json", "lng": 3438, "lat": 4585, "floor": 0, "rotation": 2, "center": [3438.5, 4585.5], "hash": 3820210661, "models": [{"type": 10, "values": [45214]}], "probably_morphFloor": true}, {"id": 41706, "name": "Iced rocks", "file": "53-71.json", "lng": 3443, "lat": 4599, "floor": 0, "rotation": 3, "center": [3443.5, 4599.5], "hash": 950759506, "models": [{"type": 10, "values": [45214]}], "probably_morphFloor": true}, {"id": 41707, "name": "Iced rocks", "file": "53-71.json", "lng": 3432, "lat": 4588, "floor": 0, "rotation": 0, "width": 2, "length": 2, "center": [3433.0, 4589.0], "hash": 1132527314, "models": [{"type": 10, "values": [45215]}], "probably_morphFloor": true}, {"id": 41707, "name": "Iced rocks", "file": "53-71.json", "lng": 3438, "lat": 4583, "floor": 0, "rotation": 1, "width": 2, "length": 2, "center": [3439.0, 4584.0], "hash": 2720141767, "models": [{"type": 10, "values": [45215]}], "probably_morphFloor": true}, {"id": 41707, "name": "Iced rocks", "file": "53-71.json", "lng": 3441, "lat": 4599, "floor": 0, "rotation": 1, "width": 2, "length": 2, "center": [3442.0, 4600.0], "hash": 2605056004, "models": [{"type": 10, "values": [45215]}], "probably_morphFloor": true}, {"id": 41749, "name": "Ice sculpture", "file": "53-71.json", "lng": 3441, "lat": 4578, "floor": 0, "rotation": 0, "length": 4, "center": [3441.5, 4580.0], "hash": 3031485884, "models": [{"type": 10, "values": [45270]}], "morphs_1": {"unk1": 953352191, "unk2": [41719, 41719, 41719, 32767, 32767, 32767, 32767, 32767, 32767, 32767, 41719, 32767, 32767, 32767, 32767, 32767, 32767, 32767, 32767, 32767, 41719, 32767, 32767, 32767, 32767, 41719, 32767, 32767, 32767, 32767, 41719, 32767, 32767, 32767, 32767, 41719, 32767, 32767, 32767, 32767, 41717, 32767, 32767, 32767, 32767, 41717, 32767, 32767, 32767, 32767], "unk3": 41717}}, {"id": 41750, "name": "Ice sculpture", "file": "53-71.json", "lng": 3442, "lat": 4578, "floor": 0, "rotation": 0, "length": 4, "center": [3442.5, 4580.0], "hash": 1815980052, "models": [{"type": 10, "values": [45266]}], "morphs_1": {"unk1": 953352191, "unk2": [41720, 41720, 41720, 32767, 32767, 32767, 32767, 32767, 32767, 32767, 41720, 32767, 32767, 32767, 32767, 32767, 32767, 32767, 32767, 32767, 41720, 32767, 32767, 32767, 32767, 41720, 32767, 32767, 32767, 32767, 41720, 32767, 32767, 32767, 32767, 41720, 32767, 32767, 32767, 32767, 41718, 32767, 32767, 32767, 32767, 41718, 32767, 32767, 32767, 32767], "unk3": 41718}}, {"id": 41751, "name": "Ice sculpture", "file": "53-71.json", "lng": 3441, "lat": 4582, "floor": 0, "rotation": 0, "width": 2, "length": 5, "center": [3442.0, 4584.5], "hash": 2310372224, "models": [{"type": 10, "values": [45236]}], "morphs_1": {"unk1": 953352191, "unk2": [41733, 41733, 41733, 32767, 32767, 32767, 32767, 32767, 32767, 32767, 41733, 32767, 32767, 32767, 32767, 32767, 32767, 32767, 32767, 32767, 41733, 32767, 32767, 32767, 32767, 41733, 32767, 32767, 32767, 32767, 41733, 32767, 32767, 32767, 32767, 41733, 32767, 32767, 32767, 32767, 41734, 32767, 32767, 32767, 32767, 41734, 32767, 32767, 32767, 32767], "unk3": 41734}}, {"id": 14503, "name": "Wilderness Sign", "file": "53-71.json", "lng": 3397, "lat": 4575, "floor": 0, "rotation": 2, "center": [3397.5, 4575.5], "hash": 1564393358, "models": [{"type": 10, "values": [14650]}]}, {"id": 14503, "name": "Wilderness Sign", "file": "53-71.json", "lng": 3403, "lat": 4581, "floor": 0, "rotation": 2, "center": [3403.5, 4581.5], "hash": 2334735077, "models": [{"type": 10, "values": [14650]}]}, {"id": 14503, "name": "Wilderness Sign", "file": "53-71.json", "lng": 3413, "lat": 4581, "floor": 0, "rotation": 1, "center": [3413.5, 4581.5], "hash": 641978190, "models": [{"type": 10, "values": [14650]}]}, {"id": 23271, "name": "Wilderness Ditch", "file": "53-71.json", "lng": 3392, "lat": 4545, "floor": 0, "rotation": 2, "length": 2, "center": [3392.5, 4546.0], "hash": 1561521154, "actions": ["Cross"], "models": [{"type": 10, "values": [24201]}], "action_cursors_0": 181}, {"id": 23271, "name": "Wilderness Ditch", "file": "53-71.json", "lng": 3393, "lat": 4545, "floor": 0, "rotation": 2, "length": 2, "center": [3393.5, 4546.0], "hash": 1241061445, "actions": ["Cross"], "models": [{"type": 10, "values": [24201]}], "action_cursors_0": 181}]